pyfra/__init__.py
pyfra/delegation.py
pyfra/idempotent.py
pyfra/remote.py
pyfra/setup.py
pyfra/shell.py
pyfra/contrib/__init__.py
pyfra/contrib/web/.gitignore
pyfra/contrib/web/LICENSE
pyfra/contrib/web/README.md
pyfra/contrib/web/__init__.py
pyfra/contrib/web/app.py
pyfra/contrib/web/config.py
pyfra/contrib/web/emailer.py
pyfra/contrib/web/forms.py
pyfra/contrib/web/models.py
pyfra/contrib/web/requirements.txt
pyfra/contrib/web/server.py
pyfra/contrib/web/migrations/README
pyfra/contrib/web/migrations/alembic.ini
pyfra/contrib/web/migrations/env.py
pyfra/contrib/web/migrations/script.py.mako
pyfra/contrib/web/migrations/versions/1582bc5883ac_.py
pyfra/contrib/web/migrations/versions/1b1532ba9506_add_user_attributes.py
pyfra/contrib/web/static/.editorconfig
pyfra/contrib/web/static/LICENSE.txt
pyfra/contrib/web/static/browserconfig.xml
pyfra/contrib/web/static/favicon.ico
pyfra/contrib/web/static/humans.txt
pyfra/contrib/web/static/icon.png
pyfra/contrib/web/static/index.html
pyfra/contrib/web/static/robots.txt
pyfra/contrib/web/static/site.webmanifest
pyfra/contrib/web/static/css/main.css
pyfra/contrib/web/static/css/reset.css
pyfra/contrib/web/static/img/background.jpg
pyfra/contrib/web/static/img/eai_logo.png
pyfra/contrib/web/static/img/excel.png
pyfra/contrib/web/static/img/icon-button-adduser.svg
pyfra/contrib/web/static/img/icon-button-admin.svg
pyfra/contrib/web/static/img/icon-button-change_password.svg
pyfra/contrib/web/static/img/icon-button-demo_form.svg
pyfra/contrib/web/static/img/logout.svg
pyfra/contrib/web/static/img/print_button.jpg
pyfra/contrib/web/static/img/icon-button-admin/user.svg
pyfra/contrib/web/static/js/main.js
pyfra/contrib/web/static/js/plugins.js
pyfra/contrib/web/static/js/vendor/jquery-3.3.1.min.js
pyfra/contrib/web/static/js/vendor/modernizr-3.6.0.min.js
pyfra/contrib/web/static/js/vendor/moment-2.23.0.js
pyfra/contrib/web/static/js/vendor/w2ui-1.5.rc1.js
pyfra/contrib/web/static/js/vendor/w2ui-1.5.rc1.min.js
pyfra-0.3.1.dist-info/LICENSE
pyfra-0.3.1.dist-info/METADATA
pyfra-0.3.1.dist-info/WHEEL
pyfra-0.3.1.dist-info/top_level.txt
pyfra-0.3.1.dist-info/RECORD
