Metadata-Version: 2.1
Name: pyfra
Version: 0.3.1
Summary: A framework for research code
Home-page: https://github.com/EleutherAI/pyfra
Author: Leo Gao
Author-email: lg@eleuther.ai
License: UNKNOWN
Platform: UNKNOWN
Classifier: Programming Language :: Python :: 3
Classifier: License :: OSI Approved :: MIT License
Classifier: Operating System :: OS Independent
Requires-Python: >=3.6
License-File: LICENSE
Requires-Dist: best-download
Requires-Dist: sqlitedict
Requires-Dist: colorama
Requires-Dist: parse
Requires-Dist: natsort
Requires-Dist: yaspin
Requires-Dist: imohash
Requires-Dist: deprecation
Provides-Extra: contrib
Requires-Dist: flask ; extra == 'contrib'
Requires-Dist: flask-login ; extra == 'contrib'
Requires-Dist: flask-wtf ; extra == 'contrib'
Requires-Dist: flask-sqlalchemy ; extra == 'contrib'
Requires-Dist: flask-migrate ; extra == 'contrib'
Requires-Dist: flask-admin ; extra == 'contrib'
Requires-Dist: flask-bootstrap ; extra == 'contrib'
Requires-Dist: pyjwt ; extra == 'contrib'
Requires-Dist: sqlalchemy ; extra == 'contrib'
Requires-Dist: wtforms[email] ; extra == 'contrib'
Requires-Dist: ansi2html ; extra == 'contrib'
